vgc_zero_lcd_teriyakigod/__init__.py
vgc_zero_lcd_teriyakigod/config.py
vgc_zero_lcd_teriyakigod/lcd.py
vgc_zero_lcd_teriyakigod/test.py
vgc_zero_lcd_teriyakigod/vgc.py
vgc_zero_lcd_teriyakigod-0.0.1.dist-info/LICENSE
vgc_zero_lcd_teriyakigod-0.0.1.dist-info/METADATA
vgc_zero_lcd_teriyakigod-0.0.1.dist-info/WHEEL
vgc_zero_lcd_teriyakigod-0.0.1.dist-info/top_level.txt
vgc_zero_lcd_teriyakigod-0.0.1.dist-info/RECORD
